cruise_llm/LLM.py
cruise_llm/__init__.py
cruise_llm/rankings/static_rankings_2025-12-19.json
cruise_llm-0.2.0.dist-info/METADATA
cruise_llm-0.2.0.dist-info/WHEEL
cruise_llm-0.2.0.dist-info/licenses/LICENSE
cruise_llm-0.2.0.dist-info/RECORD
